simpledsapp
