Metadata-Version: 1.0
Name: simpledsapp
Version: 1.0.3
Summary: A simple/dummy ChRIS DS app
Home-page: https://github.com/FNNDSC/pl-simpledsapp
Author: Rudolph Pienaar
Author-email: rudolph.pienaar@gmail.com
License: MIT
Platform: UNKNOWN
